libtwenty/__init__.py
libtwenty/assets/AGAALER.TTF
libtwenty-2.3.3.dist-info/METADATA
libtwenty-2.3.3.dist-info/WHEEL
libtwenty-2.3.3.dist-info/top_level.txt
libtwenty-2.3.3.dist-info/RECORD
